main.py
managers/__init__.py
managers/action_manager.py
managers/blueprint_manager.py
managers/blueprint_tree_manager.py
managers/mapping_manager.py
managers/widget_manager.py
port_oneclick_mw-0.1.3.dist-info/METADATA
port_oneclick_mw-0.1.3.dist-info/WHEEL
port_oneclick_mw-0.1.3.dist-info/entry_points.txt
port_oneclick_mw-0.1.3.dist-info/top_level.txt
port_oneclick_mw-0.1.3.dist-info/RECORD
