Metadata-Version: 2.4
Name: port-oneclick-mw
Version: 0.1.3
Summary: A Python middleware service for managing Port.io guides (blueprints, actions, mappings, widgets)
Author-email: Erioluwa Asiru <your.email@example.com>
License: MIT
Project-URL: Homepage, https://github.com/yourusername/port-oneclick-mw
Project-URL: Documentation, https://github.com/yourusername/port-oneclick-mw/blob/main/README.md
Project-URL: Repository, https://github.com/yourusername/port-oneclick-mw
Project-URL: Issues, https://github.com/yourusername/port-oneclick-mw/issues
Keywords: port,port.io,middleware,blueprints,automation
Classifier: Development Status :: 4 - Beta
Classifier: Intended Audience :: Developers
Classifier: License :: OSI Approved :: MIT License
Classifier: Programming Language :: Python :: 3
Classifier: Programming Language :: Python :: 3.8
Classifier: Programming Language :: Python :: 3.9
Classifier: Programming Language :: Python :: 3.10
Classifier: Programming Language :: Python :: 3.11
Classifier: Programming Language :: Python :: 3.12
Classifier: Programming Language :: Python :: 3.13
Requires-Python: >=3.8
Requires-Dist: requests>=2.31.0
Requires-Dist: python-dotenv>=1.0.0
Provides-Extra: dev
Requires-Dist: pytest>=7.0.0; extra == "dev"
Requires-Dist: black>=23.0.0; extra == "dev"
Requires-Dist: flake8>=6.0.0; extra == "dev"
